Metadata-Version: 2.1
Name: hero1
Version: 0.9
Summary: Hero
Home-page: https://github.com/danielhwkim/Hero1
Download-URL: https://github.com/danielhwkim/Hero1/archive/refs/tags/v_0_9.tar.gz
Author: Hoewon Kim
Author-email: hoewon.kim@gmail.com
License: MIT
Keywords: hero1
Platform: UNKNOWN
Classifier: Development Status :: 3 - Alpha
Classifier: Intended Audience :: Developers
Classifier: Topic :: Software Development :: Build Tools
Classifier: License :: OSI Approved :: MIT License
Classifier: Programming Language :: Python :: 3
Classifier: Programming Language :: Python :: 3.4
Classifier: Programming Language :: Python :: 3.5
Classifier: Programming Language :: Python :: 3.6
Classifier: Programming Language :: Python :: 3.10
License-File: LICENSE
License-File: LICENSE.txt
